utss/__init__.py
utss/capabilities.py
utss/models.py
utss/validator.py
utss-1.0.0.dist-info/METADATA
utss-1.0.0.dist-info/WHEEL
utss-1.0.0.dist-info/RECORD
